alibabacloud_clickhouse20230522/__init__.py
alibabacloud_clickhouse20230522/client.py
alibabacloud_clickhouse20230522/models/__init__.py
alibabacloud_clickhouse20230522/models/_attach_whitelist_template_to_instance_request.py
alibabacloud_clickhouse20230522/models/_attach_whitelist_template_to_instance_response.py
alibabacloud_clickhouse20230522/models/_attach_whitelist_template_to_instance_response_body.py
alibabacloud_clickhouse20230522/models/_change_resource_group_request.py
alibabacloud_clickhouse20230522/models/_change_resource_group_response.py
alibabacloud_clickhouse20230522/models/_change_resource_group_response_body.py
alibabacloud_clickhouse20230522/models/_create_account_request.py
alibabacloud_clickhouse20230522/models/_create_account_response.py
alibabacloud_clickhouse20230522/models/_create_account_response_body.py
alibabacloud_clickhouse20230522/models/_create_account_shrink_request.py
alibabacloud_clickhouse20230522/models/_create_backup_policy_request.py
alibabacloud_clickhouse20230522/models/_create_backup_policy_response.py
alibabacloud_clickhouse20230522/models/_create_backup_policy_response_body.py
alibabacloud_clickhouse20230522/models/_create_dbinstance_request.py
alibabacloud_clickhouse20230522/models/_create_dbinstance_response.py
alibabacloud_clickhouse20230522/models/_create_dbinstance_response_body.py
alibabacloud_clickhouse20230522/models/_create_dbinstance_shrink_request.py
alibabacloud_clickhouse20230522/models/_create_dbrequest.py
alibabacloud_clickhouse20230522/models/_create_dbresponse.py
alibabacloud_clickhouse20230522/models/_create_dbresponse_body.py
alibabacloud_clickhouse20230522/models/_create_endpoint_request.py
alibabacloud_clickhouse20230522/models/_create_endpoint_response.py
alibabacloud_clickhouse20230522/models/_create_endpoint_response_body.py
alibabacloud_clickhouse20230522/models/_create_whitelist_template_request.py
alibabacloud_clickhouse20230522/models/_create_whitelist_template_response.py
alibabacloud_clickhouse20230522-2.4.1.dist-info/LICENSE
alibabacloud_clickhouse20230522-2.4.1.dist-info/METADATA
alibabacloud_clickhouse20230522-2.4.1.dist-info/WHEEL
alibabacloud_clickhouse20230522-2.4.1.dist-info/top_level.txt
alibabacloud_clickhouse20230522-2.4.1.dist-info/RECORD
